{
    "4kSP": 2566,
    "4kSPExpanded": 4170,
    "AATI-Flags": 4645,
    "ABCORS": 32957,
    "AECS-Motion-Suppressor": 10655,
    "AGExt": 440714,
    "AIES-DeimosRast": 18327,
    "AIES-Patches": 18327,
    "AIES-TK421d": 18327,
    "AJEExtendedConfigs": 9101,
    "ANGLECANPartTweaks": 303,
    "ANGLECANProgression": 498,
    "APPLE": 971,
    "AQSS": 2460,
    "ASET-PRC": 14122,
    "ASETAgency": 126535,
    "ASETAvionics": 108326,
    "ASETProps": 190320,
    "ASSET-Mk1": 3166,
    "AT-Utils": 309449,
    "ATKPropulsionPack": 24793,
    "AVP-2kTextures": 617671,
    "AVP-4kTextures": 617671,
    "AVP-8kTextures": 617671,
    "AblativeAirbrake": 66462,
    "AbovetheSkySoyuzTMAandR7": 4281,
    "Achievements": 8434,
    "ActionGroupManager": 6256,
    "ActualSitesAirports": 3303,
    "AdjustableModPanel": 13039,
    "AdvancedFlyByWire": 28790,
    "AdvancedFlyByWire-Linux": 4948,
    "AdvancedFlyByWire-OSX": 4948,
    "AdvancedJetEngine": 253271,
    "AdvancedTextures": 6644,
    "AerospacePassengerandUtilitySystem": 7020,
    "AirParkContinued": 4745,
    "AirbusA330neo": 6220,
    "AircraftCarrierAccessories": 54659,
    "AirlineKuisine": 34604,
    "AirlockPlus": 19555,
    "AirplanePlus": 330244,
    "AirplanePlusThings": 7248,
    "AlarmEnhancements": 1961,
    "AlcubierreStandalone": 278799,
    "AllAboard": 3060,
    "AllYAll": 14142,
    "AlternateResourcePanel": 422027,
    "AlternisKerbolRekerjiggered": 5830,
    "AltimeterAutoHide": 2745,
    "AmongUsKSP": 1605,
    "AmpYearPowerManager": 258429,
    "AngaraRocketPack": 1806,
    "AnimatedAttachment": 11808,
    "AnimatedDecouplers": 202095,
    "AntaresCygnus": 85270,
    "AntennaHelper": 23765,
    "AntennaSleep": 23481,
    "AnyResContinued": 3682,
    "Ariane6": 5677,
    "Ariane6-RealFuels": 5677,
    "Asteroid-33434-scottmanley-RSS": 1173,
    "Asteroid-33434-scottmanley-Stock": 978,
    "AstraKodiakAlaskaSpaceport": 279,
    "AstraRocket3TransporterErector": 177,
    "Astrogator": 105513,
    "AstronomersVisualPack": 617671,
    "AtmosphereAutopilot": 115461,
    "AtomicTechFlags": 1634,
    "AtomicTechFlags-ATHSS": 740,
    "AtomicTechIncJunkyards": 810,
    "AtomicTechKerbalDietPills": 37,
    "AtomicTechKerbalizedNames": 431,
    "Atoren": 2305,
    "AttitudeAdjuster": 9062,
    "AugmentedReality": 6620,
    "AuroraSpaceCenter": 5738,
    "AutoAGL": 11742,
    "AutoAction": 102176,
    "AutoAsparagus": 65333,
    "AutoHibernate": 3492,
    "AutoLoadGame": 9368,
    "AutomatedAerialRefueling": 24440,
    "AutomatedScienceSampler": 78282,
    "AutomatedScreenshots": 1626,
    "AutomaticFuelCells": 2983,
    "AviationLights": 131091,
    "AvionicsSystems": 23858,
    "B9": 944759,
    "B9-PWings-Fork": 88388,
    "B9-props": 944759,
    "B9AerospaceHX": 944759,
    "B9AerospaceLegacy": 944759,
    "B9AnimationModules": 269505,
    "B9HXReconfig": 9431,
    "B9PartSwitch": 1019008,
    "B9StockPatches": 7575,
    "BAMCont": 9117,
    "BARIS": 7555,
    "BDAUITeamIcons": 2531,
    "BDAnimationModules": 327417,
    "BDArmoryContinued": 433427,
    "BDArmoryForRunwayProject": 42701,
    "BDDMP": 18100,
    "BDModularMissileParts": 25205,
    "BOMPs": 4235,
    "BOPN": 8071,
    "BOSSContinued": 1135,
    "BackgroundResources": 597081,
    "BahaEPLRedrilled": 5022,
    "BallisticFoxsNeutralTUFXProfile": 2472,
    "BallisticFoxsVintageTUFXProfile": 931,
    "BargainRocketsCont": 5299,
    "BarisBridge": 23551,
    "BasicDeltaV": 44033,
    "BasicOrbit": 61465,
    "BatteryActivatorReactivated": 2622,
    "BeamedPowerPlugin": 5972,
    "BeamedPowerPlugin-Realistic": 5972,
    "BehemothAerospaceEngineeringLargeParts": 4214,
    "Benjee10Suits": 2037,
    "BenjisHardwiredLogic": 945,
    "BetterBurnTime": 444979,
    "BetterCrewAssignment": 73566,
    "BetterEarlyTree": 8331,
    "BetterLoadSaveGame": 11244,
    "BetterSRBs": 30897,
    "BetterScienceLabsContinued": 8199,
    "BetterTimeWarpCont": 69599,
    "BetterWithScience": 1610,
    "BeyondHome": 30307,
    "BeyondSpace1999": 1042,
    "BigBen": 916,
    "Biomatic": 15072,
    "BiomaticForAll": 15072,
    "BirthOfTime": 3422,
    "BirthOfTime-CetiHomeswitch": 1049,
    "BirthOfTime-Interstellar": 2102,
    "BladeTweaks": 5986,
    "BluedogDB": 183312,
    "Blueshift": 9848,
    "BobsPanicBox": 5806,
    "BonVoyage": 93021,
    "BoosterGuidance": 7883,
    "BreakingGroundPropellerRebalance": 964,
    "Buffalo": 35540,
    "Buffalo-PlayMode-CRP": 35540,
    "Buffalo-PlayMode-ClassicStock": 35540,
    "BulbEvolved": 1160,
    "Bumblebee": 9566,
    "BuoyancyControl": 5060,
    "Bureaucracy": 2691,
    "BurstAtomicThrust": 8027,
    "BuzzardCollectors": 3469,
    "C1ustasTUFXProfiles": 1066,
    "CCTV": 31986,
    "CEDA-AeronauticsDivision": 4684,
    "CEDA-Aethon-ITS": 5089,
    "CParts": 1119,
    "CRE": 6288,
    "CST100Starliner": 9224,
    "CameraFocusChanger": 13959,
    "CameraTools": 21636,
    "CanaveralPads": 3507,
    "CapCom": 198898,
    "CapsuleCorpKerbalKolonizationProgram": 3851,
    "CareerManagerContinued": 14420,
    "CarnationREDFlexibleParts": 4188,
    "CashedowtEarthTUFXProfile": 215,
    "CelestialBodyScienceEditor": 37290,
    "ChampagneBottleRedux": 50032,
    "Chatterer": 523676,
    "ChayrolDesignOrg": 1894,
    "ChopShop": 77731,
    "Chrononaut": 831,
    "CivilianPopulation": 7298,
    "ClassicStockResources": 14348,
    "ClickThroughBlocker": 550357,
    "ColdWarAerospace": 11304,
    "CollectingSPsUSRibbonsPack": 556,
    "CollisionFXReUpdated": 16898,
    "ComfortableLanding": 45678,
    "CommNetAntennasConsumptor": 20963,
    "CommNetAntennasExtension": 71112,
    "CommNetAntennasInfo": 48408,
    "CommNetConstellation": 45695,
    "CommNetManager": 10283,
    "CommNetVisualisation": 12040,
    "CommunityCategoryKit": 703026,
    "CommunityDeltaVMaps": 18072,
    "CommunityPartsTitles": 90664,
    "CommunityPartsTitlesExtrasCategory": 90664,
    "CommunityPartsTitlesExtrasNoCCKDup": 90664,
    "CommunityResourcePack": 1494453,
    "CommunityTechTree": 813239,
    "CommunityTerrainTexturePack": 145055,
    "CommunityTraitIcons": 56224,
    "CompletelyNonAggressiveRocketry": 3226,
    "ConfigurableContainers": 318739,
    "ConnectedLivingSpace": 68757,
    "ConsistentVariants": 1044,
    "ConstantTWR": 14915,
    "ContractConfigurator": 1188321,
    "ContractConfigurator-CommNetRelays": 25275,
    "ContractConfigurator-EpicSpaceProgram": 5244,
    "ContractConfigurator-ExplorationPlus": 37470,
    "ContractConfigurator-FieldResearch": 284987,
    "ContractConfigurator-HistoryofSpaceflight-PocketEdition": 3646,
    "ContractConfigurator-HistoryofSpaceflight-RSS": 4325,
    "ContractConfigurator-HistoryofSpaceflight-Stock": 8189,
    "ContractConfigurator-JNSQ-GAP": 2461,
    "ContractConfigurator-KerbinSpaceStation": 499120,
    "ContractConfigurator-PlanesWithPurposes": 4128,
    "ContractParser": 315726,
    "ContractRewardModifier": 108747,
    "ContractsWindowPlus": 331992,
    "Corelian": 5279,
    "CorrectCoL": 39287,
    "Corvus125mTwoKerbalPod": 49040,
    "CraftHistory": 10437,
    "CraftImport": 18440,
    "CraftManager": 44257,
    "Cressida": 163,
    "CrewLight": 7588,
    "CrewQueueTwo": 42881,
    "CriticalTemperatureGauge": 36964,
    "CritterCrawler": 28251,
    "CrowdSourcedScience": 219368,
    "CrusoeSpaceIndustriesTechTree": 2556,
    "CryoEngines": 431323,
    "CryoEngines-LFO": 431323,
    "CryoEngines-NFAero": 431323,
    "CryoTanks": 190006,
    "CryoTanks-Core": 190006,
    "CustomAsteroids": 44371,
    "CustomAsteroids-Pops-OPM-Outer": 39,
    "CustomAsteroids-Pops-OPM-Reconfig": 39,
    "CustomAsteroids-Pops-Stock-Inner": 44371,
    "CustomAsteroids-Pops-Stock-Outer": 44371,
    "CustomAsteroids-Pops-Stock-Stockalike": 44371,
    "CustomParachuteMessage": 2811,
    "CustomPreLaunchChecks": 46804,
    "DARTRange": 358,
    "DE-IVAExtension": 12173,
    "DMTanks-AeroRTG": 12174,
    "DMTanks-CargoBays": 17183,
    "DMTanks-Fuselage": 14714,
    "DMTanks-SphericalTanks": 16837,
    "DMagicOrbitalScience": 612044,
    "DMagicScienceAnimate": 167948,
    "DSEV": 17631,
    "DSEV-PlayMode-CRP": 17631,
    "DSEV-PlayMode-ClassicStock": 17631,
    "DSEV-PlayMode-Pristine": 17631,
    "DTV2": 7733,
    "DaedalusConsortiumMegastationsContinued": 1352,
    "DangItContinued": 57333,
    "DangerAlertsContinued": 28252,
    "DarkMultiPlayer": 119237,
    "DatedQuickSaves": 32082,
    "DavonSupplyMod": 20651,
    "DavonTCsystemsMod": 1847,
    "DeadlyReentry": 490726,
    "DecalStickers": 27846,
    "Decalc-o-mania": 9996,
    "DecoupleWithControl": 9256,
    "DecouplerShroud": 50805,
    "DeepFreeze": 163760,
    "DeepSkyCore": 23974,
    "DeepSpaceSurfaceHabitatUnitPack": 21769,
    "DefaultActionGroups": 27004,
    "DeployableBatteries": 9865,
    "DeployableEngines": 189551,
    "DescentMode": 4062,
    "DestructionEffects": 81819,
    "DiRT": 7168,
    "DiazosLandingHeight": 13132,
    "DisconnectingStrutBugFix": 776,
    "DistantObject": 46976,
    "DistantObject-default": 46976,
    "DockRotate": 86520,
    "DockSafe": 13087,
    "DockingCamKURS": 51565,
    "DockingPortAlignmentIndicator": 449986,
    "DockingPortDescriptions": 4399,
    "DodoLabsStockalikeElectron": 10551,
    "DongFangHongPlatformSeries": 1475,
    "DoubleIt": 1091,
    "DoubleTapBrakes": 3773,
    "DrKermnassusParts": 1468,
    "DraggableAltimeter": 11198,
    "DraggableNavball": 17585,
    "DreskillerBase": 1532,
    "Droplet": 6607,
    "DunaDirect": 15294,
    "DunaIncubatorHabitat": 2333,
    "DuoPods": 1349,
    "DynamicBatteryStorage": 267291,
    "ESLDJumpBeacons": 22934,
    "ETT": 50384,
    "EVAEnhancementsContinued": 84807,
    "EVAHandrailsPackContinued": 77377,
    "EVAParachutes": 144099,
    "EVARefueling": 2361,
    "EVARepairs": 767,
    "EVAStruts": 59388,
    "EVATransfer": 53791,
    "EarnYourStripes": 24083,
    "EasyBoard": 35049,
    "EasyVesselSwitch": 146996,
    "Ecumenopolis": 4901,
    "EditorExtensionsRedux": 283936,
    "ElectronStrongbackErector": 652,
    "ElephantEngine": 12985,
    "EnduranceSpaceExplorationSystem": 5431,
    "EngineIgnitorReignited": 21817,
    "EngineLightRelit": 71570,
    "EnvironmentalVisualEnhancements": 125254,
    "EnvironmentalVisualEnhancements-HR": 2518277,
    "EquentPlanetpack": 1077,
    "EtherealFrigus": 1273,
    "EvaFollower": 25065,
    "EvaFuelCont": 39809,
    "ExperimentTracker": 22051,
    "ExplodiumBreathingEngines": 8716,
    "ExtensiveEngRptContinued": 23056,
    "ExtrasolarPlanetsBeyondKerbol-stock": 86356,
    "FASA": 119843,
    "FIG": 789,
    "FMRSContinued": 151023,
    "FTLDriveContinued": 57793,
    "FairingFix": 4243,
    "FanAOAnRotorTorque": 1656,
    "FarFutureTechnologies": 25495,
    "FelineUtilityRovers": 167310,
    "FerramAerospaceResearchContinued": 601237,
    "FieldTrainingFacility": 14621,
    "FieldTrainingLaboratory": 12906,
    "FillitUp": 11905,
    "FilterExtensions": 132866,
    "FilterExtensionsDefaultConfig": 132866,
    "FinalDawn": 1936,
    "FinalFrontier": 241091,
    "Firespitter": 1199016,
    "FirespitterCore": 1199016,
    "FirespitterExtended": 7990,
    "FirespitterResourcesConfig": 1199016,
    "FishyAntiMissileSpam": 1776,
    "FlagRotateCont": 16208,
    "FlagTexts": 3773,
    "FlagsandNumbers": 2513,
    "FlatBtmShtlSys": 11158,
    "FlexibleDocking": 62968,
    "FlightPlan": 24634,
    "FlightTracker": 16271,
    "FlyingSaucers": 4322,
    "FossilsMechazilla": 162,
    "FoxDefenseContracts": 20645,
    "FuelWings": 18339,
    "FullAutoStrut": 28668,
    "FuseBoxContinued": 51535,
    "FutureTechnologiesExpansion-FrontierAeronautics": 3163,
    "GPP": 183874,
    "GPPCloudsHighRes": 183874,
    "GPPCloudsLowRes": 183874,
    "GPPSecondary": 183874,
    "GPPTextures": 183874,
    "GPWS": 2336,
    "GRAPES": 576,
    "GemstoneLV": 284,
    "GenesStarRemaster": 1741,
    "GerryAndersonsSpace1999Pack": 4481,
    "GolderSystem": 6343,
    "GolderSystemKerbolEdition": 2948,
    "GoliathPatch": 2951,
    "Goodspeed": 8948,
    "Grannus-RibbonPack-FromGEP": 14660,
    "Grannus-RibbonPack-FromGPP": 183874,
    "GrannusExpansionPack": 14660,
    "GrannusExpansionPack-CommNet": 14660,
    "GrannusExpansionPack-Primary": 14660,
    "GrannusExpansionPack-Rescale": 14660,
    "GravityTurnContinued": 88597,
    "GreenKerbs": 1034,
    "GreenSkullRevived": 1915,
    "GrondsMicrometeoriteShield": 331,
    "GroundConstruction": 248171,
    "GroundConstruction-Core": 248171,
    "GroundEffect": 5764,
    "GroundProximity": 6877,
    "Grounded": 19184,
    "HADD": 2425,
    "HafCoSpaceCenter": 3213,
    "Halloween": 454,
    "Hangar": 93748,
    "HangarGrid": 809,
    "HangerExtenderExtended": 295313,
    "Harmony2": 35285,
    "HaystackReContinued": 21544,
    "Headlines": 817,
    "HeapPadder": 5174,
    "HeatControl": 225826,
    "Heisenberg": 15140,
    "Heisenberg-PlayMode-CRP": 15140,
    "Heisenberg-PlayMode-ClassicStock": 15140,
    "Heisenberg-PlayMode-Pristine": 15140,
    "Heisenberg-PlayMode-Simplified": 15140,
    "Helvica": 5507,
    "Heracleitus": 2854,
    "HideEmptyTechNodes": 274289,
    "Historian-expanded": 9713,
    "HooliganLabsAirships": 60162,
    "HotSpot": 29383,
    "HullcamVDSContinued": 201506,
    "HyperDriveMod": 2843,
    "HyperPropulsionSciFiEnginePack": 9942,
    "IDFlagsandDecals": 19585,
    "IONRCS": 31002,
    "ISRUThanksButNoTanks": 4603,
    "IXSWarpship-Blueshift": 0,
    "IXSWarpshipOS": 45655,
    "ImageViewerCont": 13202,
    "Impact": 81570,
    "ImpossibleInnovations": 16686,
    "ImprovedTreeEnginePlacement": 13651,
    "ImprovedUpdatedChaseCam": 4989,
    "IndicatorLights": 268237,
    "IndicatorLightsCommunityExtensions": 55434,
    "InfernalRoboticsNext": 415504,
    "InfernalRoboticsRealismOverhaul": 18252,
    "InlineBallutes": 23093,
    "InnerLock": 6820,
    "IntakeAirDrainIt": 1175,
    "IntegratedStackDecouplers": 15626,
    "InterKalactic2": 1958,
    "IntercolorCRERecolours": 596,
    "InternalRCS": 17689,
    "InterstellarFuelSwitch": 1014707,
    "InterstellarFuelSwitch-Core": 1014707,
    "InterstellarMassAccelerator": 7905,
    "InterstellarRedistributable": 15147,
    "InterstellarTechnologies": 7075,
    "JDiminishingRTG": 3637,
    "JNSQ": 32277,
    "JNSQ-KSRGAP": 966,
    "JNSQ-RealDate": 1453,
    "JNSQ-RibbonPack": 32277,
    "JPL-RSS": 5651,
    "JSIAdvancedTransparentPods": 89142,
    "JSIPartUtilities": 80102,
    "JSat": 3441,
    "JX2Antenna": 82484,
    "JackOLantern": 2032,
    "JamesWebbForKerbal": 11571,
    "JanetsPlanets": 258,
    "JanitorsCloset": 349355,
    "JaprisStellarNeighborhood": 4193,
    "JetSoundsContinued": 12343,
    "K2CommandPodCont": 51194,
    "KAS": 210535,
    "KASAFlagPackandTUFXProfile": 2120,
    "KDEX": 18632,
    "KE-01-RTG": 3713,
    "KEI": 84962,
    "KGEx": 7959,
    "KIS": 228973,
    "KKL": 3345,
    "KKsDeltaPack": 12743,
    "KOOSE": 14494,
    "KRASH": 157210,
    "KRnD": 10370,
    "KS3P": 66901,
    "KSCExtended": 47144,
    "KSCHarbor": 8596,
    "KSCSwitcher": 296500,
    "KSIWheels": 3459,
    "KSP-AVC": 103951,
    "KSP-Data-Export": 800,
    "KSP-PartVolume": 2841,
    "KSP-Recall": 130442,
    "KSPArtemisSuit": 2311,
    "KSPBugReport": 192,
    "KSPBurst": 18115,
    "KSPBurst-Lite": 18115,
    "KSPCasherCont": 14304,
    "KSPCommunityFixes": 3933,
    "KSPDataDump": 1818,
    "KSPDev-LogConsole": 1430,
    "KSPInterstellarExtended": 718052,
    "KSPLogger": 4488,
    "KSPRescueContractFix": 3231,
    "KSPRescuePodFix": 28742,
    "KSPSecondaryMotion": 8124,
    "KSPW00tNow": 667,
    "KSPWheel": 190254,
    "KSTS": 13490,
    "KVASS": 2262,
    "KVVContinued": 63352,
    "KWRocketryRebalanced": 150511,
    "KXAPI": 47326,
    "Kaboom": 7188,
    "KaioSpaceKSPStarship2021": 2044,
    "KaptainsLog": 11308,
    "Karbonite": 438292,
    "Kartographer": 12501,
    "KeR-7": 4002,
    "KeepItStraight": 26678,
    "KerBalloons": 4665,
    "KerbCam-Continued": 5384,
    "KerbalActuators": 77114,
    "KerbalAircraftExpansion": 27709,
    "KerbalAlarmClock": 1021698,
    "KerbalAnimationSuiteCont": 8586,
    "KerbalAtomics": 519325,
    "KerbalAtomics-NTRModSupport": 519325,
    "KerbalAtomics-NTRsUseLF": 519325,
    "KerbalChangelog": 56134,
    "KerbalConstructionTime": 141616,
    "KerbalDangerous": 604,
    "KerbalEngineerRedux": 1306456,
    "KerbalField": 19128,
    "KerbalFlightIndicators": 57027,
    "KerbalFoundriesContinued": 196487,
    "KerbalGPSRevived": 30233,
    "KerbalHealth": 26589,
    "KerbalHotSeatCont": 9143,
    "KerbalImprovedSaveSystem": 35455,
    "KerbalInventoryForAll": 8662,
    "KerbalInventorySystemNoFun": 48044,
    "KerbalJointReinforcementContinued": 757528,
    "KerbalJointReinforcementNext": 610290,
    "KerbalKomets": 11661,
    "KerbalKonstructs": 80576,
    "KerbalKrashSystem": 10284,
    "KerbalLaunchFailure": 41625,
    "KerbalMiniShuttle": 4343,
    "KerbalMotorbikes": 468,
    "KerbalNRAP": 54911,
    "KerbalObjectInspectorCont": 9791,
    "KerbalOccupationColors": 6356,
    "KerbalPlanetaryBaseSystems": 544695,
    "KerbalRenamer": 81212,
    "KerbalSimpit": 106,
    "KerbalSpacePonies": 12205,
    "KerbalTelemetry": 3303,
    "KerbalTubes": 4524,
    "KerbalWeatherProject": 7514,
    "KerbalWeatherProject-Lite": 2270,
    "KerbalXMod": 37328,
    "Kerbalism": 158041,
    "Kerbalism-Config-Default": 158041,
    "Kerbalism-Config-RO": 49742,
    "Kerbalism-Config-ScienceOnly": 4391,
    "KerbalismCompanionCalculator": 2523,
    "KerbalizedBocaChica": 769,
    "KerbalizedFlagpack": 15260,
    "KerbalizedSuits": 3615,
    "KerbinRoverRedux": 1467,
    "KerbinSideRemastered": 37783,
    "KerbinSideRemasteredGAP": 7168,
    "KerbinSideRemasteredGapExtras": 2247,
    "KerbinSideRemasteredTLA": 1941,
    "KerbinsSmolRings": 762,
    "KerbnetController": 40320,
    "KerboKatzSmallUtilities": 39887,
    "KerboKatzSmallUtilities-DailyFunds": 39887,
    "KerboKatzSmallUtilities-DestroyAll": 39887,
    "KerboKatzSmallUtilities-FPSLimiter": 39887,
    "KerboKatzSmallUtilities-FPSViewer": 39887,
    "KerboKatzSmallUtilities-KerbalScienceExchange": 39887,
    "KerboKatzSmallUtilities-ModifiedExplosionPotential": 39887,
    "KerboKatzSmallUtilities-PhysicalTimeRatioViewer": 39887,
    "KerboKatzSmallUtilities-RecoverAll": 39887,
    "KerboKatzUtilities": 102684,
    "KerbolOrigins": 33267,
    "Kerbonov": 12322,
    "Kerbulator": 26378,
    "KerwisChinaAerospacePack": 3298,
    "KesslerSyndrome": 2182,
    "KeyNode": 3700,
    "KipDockingPorts": 8132,
    "KipEng-Agency": 8132,
    "KipLowProfileHubs": 2989,
    "KipardSkylon": 4199,
    "KiwiTechTree": 6941,
    "KochisIndustries": 126,
    "KolyphemusSystemContinued": 6872,
    "Komplexity": 410,
    "Konstruction": 334335,
    "Kopernicus": 886197,
    "KopernicusExpansionContinued-CometTail": 66771,
    "KopernicusExpansionContinued-Common": 66771,
    "KopernicusExpansionContinued-EVAFootprints": 66771,
    "KopernicusExpansionContinued-EmissiveFX": 66771,
    "KopernicusExpansionContinued-ModularNoise": 66771,
    "KopernicusExpansionContinued-ProceduralGasGiants": 66771,
    "KopernicusExpansionContinued-ReentryEffects": 66771,
    "KopernicusExpansionContinued-RegionalPQSMods": 66771,
    "KopernicusExpansionContinued-VertexHeightDeformity": 66771,
    "KopernicusExpansionContinued-VertexHeightMap": 66771,
    "KopernicusExpansionContinued-Wormholes": 66771,
    "KourageousTourists": 2980,
    "KramaxAutopilotContinued": 39229,
    "Kronometer": 21857,
    "KspCraftOrganizer": 98,
    "KurrikaneExpanded": 18308,
    "KylandersFlagPack": 1684,
    "LCDLaunchCountDown": 25416,
    "LIME": 535,
    "LTechContinued": 9016,
    "LadderWarp": 451,
    "LanderCanMk12": 4912,
    "Landertron": 15870,
    "LaserDist": 14099,
    "LaunchNumbering": 34097,
    "LegacyVariants": 6987,
    "LessRealKerbalism": 1196,
    "LessRealThanReal": 1549,
    "LessSimpleISRU": 2039,
    "LightsOutRelit": 11303,
    "LionheadAerospaceCircularSolarPanels": 1873,
    "LiteFuels": 1234,
    "LoadingScreenManager": 68427,
    "LoadingTipsPlus": 26180,
    "LongMarch10CZ10": 3992,
    "LongMarch11CZ11": 4471,
    "LongMarch5CZ5": 5672,
    "LongMarch9CZ9": 2745,
    "LosslessISRU": 916,
    "LunaMultiplayer": 117813,
    "M-ISPx2": 4907,
    "MADLAD": 4228,
    "MANGO": 814,
    "MEPS": 3431,
    "MEVHeavyIndustries": 4603,
    "MK12PodIVAReplacementbyASET": 38815,
    "MK1StkOpenCockpit": 28318,
    "MOARStationScience": 7434,
    "MOISTUnderwaterTechnologies": 36388,
    "MOLE": 19143,
    "MOLE-PlayMode-CRP": 19143,
    "MOLE-PlayMode-ClassicStock": 19143,
    "MOLE-PlayMode-Pristine": 19143,
    "MS-SRBs": 3803,
    "MSP3000": 28426,
    "MSP3000a": 2891,
    "MagiCore": 73216,
    "MagpieMods": 29486,
    "MakingAlternateHistory": 7323,
    "MalemuteRover": 169845,
    "MandatoryRCS": 9385,
    "MandatoryRCSPartPack": 15198,
    "ManeuverNodeEvolved": 69547,
    "ManeuverQueue": 16258,
    "MarkIVSpaceplaneSystem": 170442,
    "MastodonPatch": 2116,
    "MaterialExtensionsForRealChute": 6257,
    "Measurizer": 220,
    "MechJebForAll": 164243,
    "MelantuAtmosphericHarvesting": 978,
    "MemGraph": 27459,
    "MemorialWall": 2813,
    "MicroSatRevived": 30334,
    "MidweeksGreenTUFXConfig": 559,
    "MidweeksOriginsTUFXConfig": 179,
    "MidweeksTUFXConfig": 1427,
    "MinAmbLightUpd": 5335,
    "MiniMoke": 395,
    "MiniSampleReturnCapsule": 13116,
    "MinmusSpaceCenter": 1837,
    "MinorPlanetsExpansion": 6023,
    "MinorPlanetsExpansionRevived": 2693,
    "MiporiaPlanetPack": 4146,
    "MissingHistory": 73401,
    "MissingRobotics": 5866,
    "MissionController2": 30209,
    "Mk-33": 8077,
    "Mk-X": 15479,
    "Mk1CabinHatch": 41913,
    "Mk1CockpitIVAReplbyASET": 30605,
    "Mk1LanderCanIVAReplbyASET": 32141,
    "Mk2Expansion": 297925,
    "Mk2PodWhite": 2231,
    "Mk2Y": 2391,
    "Mk3Expansion": 162984,
    "Mk3HypersonicSystems": 31359,
    "MoarFEConfigs": 22666,
    "MoarKerbals": 2330,
    "ModActions": 9586,
    "ModularLaunchPads": 107910,
    "ModuleAnimGenericResourceUsage": 966,
    "ModuleAnimateGenericEffects": 5620,
    "ModuleSequentialAnimateGeneric": 7059,
    "MoneroFlags": 2657,
    "MonthlyBudgets": 16003,
    "MoreHitchhikers": 3774,
    "MoreTerraWorlds": 3183,
    "MunarIndustriesFTX": 72614,
    "Muniant": 1184,
    "NASA-CountDown": 44875,
    "NEBULADecalsContinued": 29895,
    "NGC3371-Skybox": 7396,
    "NIMBY": 8389,
    "NKRsDEM": 23335,
    "NMSG": 57435,
    "NSIBDAcMissionEditorPatch": 787,
    "NanoGauges": 29963,
    "NavBallAdjustor": 22421,
    "NavBallTextureChangerUpdated": 2129,
    "NavHudRenewed": 19067,
    "NavUtilitiesUpdated": 584,
    "NavballDockAlignIndCE": 92044,
    "NearFutureAeronautics": 102846,
    "NearFutureConstruction": 725525,
    "NearFutureElectrical": 816097,
    "NearFutureElectrical-Core": 816097,
    "NearFutureElectrical-DecayingRTGs": 816097,
    "NearFutureExploration": 105623,
    "NearFutureLaunchVehicles": 415300,
    "NearFutureProps": 410432,
    "NearFuturePropulsion": 824436,
    "NearFuturePropulsionXenonHETs": 824436,
    "NearFutureSolar": 889468,
    "NearFutureSolar-Core": 889468,
    "NearFutureSpacecraft": 754164,
    "NearFutureSpacecraft-OrbitalLFOEngines": 754164,
    "NehemiahEngineeringOrbitalScience": 40938,
    "NeptuneCamera": 10045,
    "NetherdyneMassDriver": 1847,
    "NewShepard": 4596,
    "NewTantares": 102885,
    "NewTantaresLV": 72973,
    "NextStarIndustries": 7792,
    "NibiruSystem": 5248,
    "NiceMKseriesBody": 33463,
    "No-Texture-Atlas-5": 430,
    "No-Texture-CST-100": 560,
    "NoCrewRequirementContinued": 21108,
    "NodeHelper": 7212,
    "NodeSplitter": 3012,
    "NorthKerbinDynamicRenewed": 8326,
    "NorthKerbinDynamics": 109718,
    "NotSoSimpleConstruction": 8819,
    "Notes2Log": 1248,
    "NovaPunchRebalanced": 23343,
    "NovaPunchRebalanced-Freyja": 23343,
    "NovaPunchRebalanced-Odin": 23343,
    "NovaPunchRebalanced-Thor": 23343,
    "Nuke-TinyPartsRefueled": 2752,
    "ODFC-Refueled": 5016,
    "ODFC-Refueled-CopyPatches": 972,
    "ODFC-Refueled-ModifyPatches": 1241,
    "OPTReconfig": 132676,
    "OPTSpacePlaneMain": 23486,
    "OPTSpacePlaneParts": 178124,
    "ORANGE": 1070,
    "OSEWorkShopReworked": 13941,
    "OctosatContinued": 59551,
    "Oddiseo": 508,
    "OhScrap": 6495,
    "OldPartsRedux": 10499,
    "Olympic1ARPIcons": 21642,
    "OmicronFlyingSpaceCar": 3046,
    "OneWindow": 9113,
    "OrbitalColony": 34517,
    "OrbitalTug": 15201,
    "OreEngines": 1062,
    "OreToParts": 221,
    "OutOfGalaxySkybox": 5165,
    "OuterKerbin": 7826,
    "OuterPlanetsMod": 180850,
    "PADContinued": 14350,
    "PAPILights": 18870,
    "PAWRangeBuff": 896,
    "PAWS": 1271,
    "PEAR": 921,
    "PEBKACIndustriesLaunchEscapeSystem": 55463,
    "PLUM": 873,
    "PRUNES": 677,
    "PWBFuelBalancerRestored": 12682,
    "PangolinMechanicsToolkit": 940,
    "PanoceanCanal": 346,
    "Parallax": 131507,
    "Parallax-StockTextures": 131507,
    "ParkingBrake": 16437,
    "PartCommanderCont": 39024,
    "PartInfo": 10003,
    "PartOverhaulIntegration": 1192,
    "PartWizardContinued": 21509,
    "PartlyColoredSuits": 2834,
    "PatchManager": 227971,
    "Pathfinder": 38206,
    "Pathfinder-PlayMode-CRP": 38206,
    "Pathfinder-PlayMode-ClassicStock": 38206,
    "Pathfinder-PlayMode-Pristine": 38206,
    "Pathfinder-PlayMode-Simplified": 38206,
    "PayToPlay": 704,
    "PersistentRotation": 214778,
    "PersistentRotationUpgraded": 34813,
    "PersistentThrust": 20023,
    "PhoenixIndustries": 10887,
    "PhotonSailor": 106081,
    "PhysicsRangeExtender": 301817,
    "PicoPort": 24924,
    "PicoPort4AllSizes": 4654,
    "PicoPortShielded": 6893,
    "PilotAssistant": 384107,
    "PitchPerfect": 1143,
    "PlaneMode": 17141,
    "PlanetDunope": 1637,
    "PlanetOrigins": 1098,
    "PlanetShine": 255146,
    "PlanetShine-Config-Default": 255146,
    "PlanetWiki": 29733,
    "PlanetaryDiversity": 4259,
    "PlanetaryStationCores": 7469,
    "PlanningNode": 1000,
    "PlayYourWay": 1733,
    "PlusFlags": 5357,
    "PolishTranslation": 28498,
    "PortraitStats": 92718,
    "PreciseEditor": 22698,
    "PreciseManeuver": 140418,
    "PreciseNode": 32520,
    "PrecursorsPlanetPack": 1010,
    "ProbeControlRoomRecontrolled": 19583,
    "ProbeControlUnlimiter": 655,
    "ProbesBeforeCrew": 38677,
    "ProbesPlus": 47223,
    "ProceduralFairings": 881348,
    "ProceduralFairings-ForEverything": 243598,
    "ProceduralParts": 628067,
    "ProgressParser": 334089,
    "ProgressiveColonizationSystem": 6467,
    "ProjectManager": 14382,
    "ProvenanceAerospace": 1558,
    "Pteron": 2592,
    "PureElectricEngines": 44195,
    "QuantumStrutsContinued": 48323,
    "QuazSpaceTUFXConfig": 2320,
    "QuickBrake": 22052,
    "QuickContracts": 13553,
    "QuickCursorHider": 12230,
    "QuickExit": 26757,
    "QuickFineControl": 11168,
    "QuickGoTo": 23066,
    "QuickHide": 15764,
    "QuickIVA": 17811,
    "QuickMute": 17799,
    "QuickRevert": 14154,
    "QuickSAS": 13131,
    "QuickSearch": 68710,
    "QuickStart": 28060,
    "QuizTechAeroPackContinued": 132598,
    "RCSBuildAid": 32195,
    "RCSBuildAidCont": 169002,
    "RCSLandAid": 135109,
    "REKT": 23721,
    "REPOSoftTech-Agencies": 258429,
    "RLAReborn": 25939,
    "RN-MiscParts": 10194,
    "RN-SalyutStations": 152629,
    "RN-Skylab": 108819,
    "RN-SovietProbes": 148240,
    "RN-SovietRockets": 183837,
    "RN-SovietSpacecraft": 103012,
    "RN-USProbesPack": 193815,
    "RN-USRockets": 140397,
    "RN8474-8300-Skybox": 2209,
    "ROCapsules": 45057,
    "ROEngines": 53389,
    "ROLib": 40702,
    "ROSolar": 32939,
    "ROTanks": 42694,
    "RP-0": 557518,
    "RP-1-ExpressInstall": 2695,
    "RP-1-ExpressInstall-Graphics-High": 3309,
    "RP-1-ExpressInstall-Graphics-Low": 3309,
    "RP-1-ExpressInstall-Graphics-Medium": 3309,
    "RSS-CanaveralHD": 10542,
    "RSSDateTimeFormatter": 199197,
    "RSSTextures16K": 748092,
    "RSSTextures2048": 748092,
    "RSSTextures4096": 748092,
    "RSSTextures8192": 748092,
    "RSSVE-HR": 51569,
    "RSSVE-LR": 51569,
    "RVE64kKerbinCloudsforSpectra": 7964,
    "RadialEngineForSpacecraft": 5848,
    "RadioFreeKerbin": 10241,
    "RaginCaucasian": 84889,
    "RasterPropMonitor": 1158174,
    "RasterPropMonitor-Core": 1158174,
    "RationalHydroDynamics": 2345,
    "RationalResources": 40831,
    "RationalResourcesAluminium": 40831,
    "RationalResourcesBlacksmith": 40831,
    "RationalResourcesCompanion": 40831,
    "RationalResourcesKerbalism": 40831,
    "RationalResourcesKerbalismRF": 40831,
    "RationalResourcesNuclearFamily": 40831,
    "RationalResourcesParts": 40831,
    "RationalResourcesRCSFamily": 40831,
    "RationalResourcesSSPXRTanks": 40831,
    "RationalResourcesSquad": 40831,
    "RationalResourcesTACLS": 40831,
    "ReCoupler": 36082,
    "ReStock": 384864,
    "ReStockPlus": 384864,
    "RealAntennas": 41245,
    "RealBattery": 9015,
    "RealChute": 589575,
    "RealExoplanets": 15783,
    "RealFuels": 714665,
    "RealFuels-Stock": 6327,
    "RealHeat": 383928,
    "RealPlume": 722150,
    "RealPlume-StockConfigs": 473993,
    "RealSolarSystem": 958182,
    "RealSolarSystem-LaunchSiteExpansion": 4643,
    "RealTimeClock2": 5608,
    "RealismEnvironmentalOverhaul": 1633,
    "RealismOverhaul": 956943,
    "RealismOverhaulCraftFiles": 956943,
    "RealisticAtmospheres": 26229,
    "RealisticPowerDraw": 1842,
    "RealisticReStockAndProceduralTanks": 903,
    "RecoveryController": 111502,
    "RecycledParts": 55138,
    "RecycledPartsAtomicAge": 55138,
    "RecycledPartsFTmNAtomicRockets": 55138,
    "RecycledPartsFTmNImprovedAtomicRockets": 55138,
    "RecycledPartsFarscape": 55138,
    "RecycledPartsLVNClusters": 55138,
    "RecycledPartsMk2Essentials": 55138,
    "RecycledPartsMk2KISContainers": 55138,
    "RecycledPartsMk2Lightning": 55138,
    "RecycledPartsMk2SolarBatteries": 55138,
    "RecycledPartsOrgamiFoldableAssets": 55138,
    "RecycledPartsRSCapsuledyne": 55138,
    "RecycledPartsSpareParts": 55138,
    "RecycledPartskal9000": 55138,
    "RedOnion": 7324,
    "RedSpiderSkybox": 1839,
    "ReentryParticleEffect": 39124,
    "RemoteTech": 487521,
    "RemoteTechRedevAntennas": 59444,
    "RemoteTechStockConfigs": 4643,
    "ResearchBodies": 59053,
    "ResonantOrbitCalculator": 32354,
    "ResourceMonitors": 1891,
    "RestockRigidLegs": 384864,
    "RetractableLiftingSurface": 228261,
    "RetroFuture": 16999,
    "Ringworld": 1239,
    "RocketEmporium": 7427,
    "RocketSoundEnhancement": 14767,
    "RocketSoundEnhancement-Config-Default": 14767,
    "Rocketology": 1220,
    "RoutineMissionManager": 30109,
    "SASAG": 2913,
    "SAVE": 1496,
    "SCANsat": 864748,
    "SDHI-ServiceModuleSystem": 66928,
    "SDHI-SharedAssets": 66928,
    "SDHI-StrobeOMatic": 7480,
    "SHADO": 687,
    "SIMPLEXAssembly": 927,
    "SIMPLEXKerbalism": 8373,
    "SMURFF": 25021,
    "SOS": 2518,
    "SRMGimbal": 862,
    "SSRSS-Rescale": 84710,
    "SSTOProject": 8794,
    "STMsFFRibbonPackExpeditionRibbons": 16998,
    "SVE-HighResolution": 759003,
    "SVE-LowResolution": 759003,
    "SVE-MediumResolution": 759003,
    "SVE-Terrain": 154484,
    "SXTContinued": 225404,
    "SafeBrakes": 6448,
    "SafeChute": 95221,
    "Scatterer": 1178417,
    "Scatterer-config": 1178417,
    "Scatterer-sunflare": 1178417,
    "SciFiVisualEnhancements-WeimaranersTweaks": 3884,
    "SciRev": 1720,
    "Science-Full-Reward": 32493,
    "Science-Full-Transmit": 24495,
    "ScienceAlert": 157260,
    "ScienceLabInfo": 10944,
    "SciencePancake": 3460,
    "ScienceRelay": 92187,
    "ScienceRolesFinalFrontierRibbonPack": 18255,
    "ScienceSituationInfo": 27600,
    "ScrapYard": 30085,
    "SemiSaturatableRW": 167794,
    "SensiblePumpsCont": 19994,
    "SensibleScreenshot": 11347,
    "SensorPackageforKerbalism": 841,
    "SeparatorDestroyer": 2583,
    "SerialIO": 5989,
    "ServiceBayLimiter": 320,
    "SevenWorldsOfSlippist-1": 6166,
    "ShadowWorksStockalikeSLSandMore": 22531,
    "ShangshengOrbital": 4764,
    "ShipEffectsContinued": 18529,
    "ShipManifest": 78354,
    "ShipSaveSplicer": 12963,
    "ShowFPS": 22530,
    "ShuttleEVASuit": 2134,
    "ShuttleLiftingBodyCormorantAeronology": 113406,
    "SigmasRSSTUFXProfiles": 1386,
    "SignalDelay": 8477,
    "SimpleAdjustableFairings": 107944,
    "SimpleAdjustableFairings-KWRocketry": 70750,
    "SimpleConstruction": 60088,
    "SimpleFuelSwitch": 24924,
    "SimpleLogistics": 7368,
    "SimpleOrbitCalculator": 742,
    "SimpleRepaint": 1890,
    "SimplexPropulsion": 1217,
    "SimplexTechTree": 19871,
    "Singularity": 7124,
    "SixCrewScienceLab": 52329,
    "SixSeatMk3cockpit": 52890,
    "SlingShotterReslung": 20751,
    "SmartActuation": 12552,
    "SmartDockingAid": 3673,
    "SmartParts": 110719,
    "SmartStage": 43879,
    "SmartTank": 5684,
    "SnackTank": 970,
    "Snacks": 91442,
    "Snarkiverse": 4935,
    "SoilerPanels": 1694,
    "SolarCycleSimulator": 1404,
    "SolarScience": 51496,
    "SolidPropulsionIndustries": 5007,
    "SolverEngines": 589087,
    "SoundingRockets": 89600,
    "Soylent": 12921,
    "SpaceAge": 26473,
    "SpaceDust": 21803,
    "SpaceFrontierTechnologies": 2247,
    "SpaceLaunchSystemPartPack": 35443,
    "SpaceLink": 12485,
    "SpaceProgramFunding": 1133,
    "SpaceTuxLibrary": 148200,
    "SpaceXLaunchVehicles": 172958,
    "SpaceXLaunchVehicles-StockSize": 172958,
    "SpaceXLegs": 335616,
    "SpaceXSuits": 5658,
    "SpaceY-Lifters": 342593,
    "SpacedocksRedeployed": 6971,
    "SpacetuxSA": 134047,
    "SpecialDelivery": 7293,
    "Spectra": 89763,
    "SpeedUnitAnnex": 41385,
    "StackInlineLightPatches": 1018,
    "StackInlineLights": 1085,
    "StageRecovery": 289102,
    "StagedAnimation": 8866,
    "StandardPropulsionSystems": 10862,
    "StarLinkSatellitePack": 7229,
    "Starbase": 412,
    "StarshipLaunchExpansion": 4583,
    "StateFundingContinued": 34449,
    "StationKeeping": 22109,
    "StationPartsExpansionRedux": 380196,
    "StationPartsExpansionRedux-IVAs": 380197,
    "StationScienceContinued": 118106,
    "StationalConstructs": 7109,
    "SteamGaugesRecalibrated": 2541,
    "SteeringTweaker": 3306,
    "StockDefaultSettings": 1386,
    "StockPlanetaryUniversalRevamp": 1781,
    "StockRingTextures": 457,
    "StockScatterColliderEnablerPatch": 2591,
    "StockTKS": 2873,
    "StockVisualEnhancements": 759003,
    "StockWaterfallEffects": 25922,
    "StockalikeMiningExtension": 86815,
    "StockishProjectOrion": 9212,
    "StoreMyReports": 2664,
    "StorkDeliverySystem": 2643,
    "StrangeNewWorlds": 3327,
    "Strategia": 90723,
    "StructuralTubing": 14270,
    "SuperHeavyBoostersHistoricalNexus": 17635,
    "SuperfluousNodes": 6141,
    "SurfaceAttachableControl": 1924,
    "SurfaceLights": 48911,
    "SystemHeat": 31169,
    "SystemHeat-Converters": 31169,
    "SystemHeat-FissionEngines": 31169,
    "SystemHeat-FissionReactors": 31169,
    "SystemHeat-Harvesters": 31169,
    "TACLS": 597081,
    "TACStickyControls": 6558,
    "TALRadiallyAttachedExperimentalDataStorageContainer": 5713,
    "TDAdvancedPropulsionSystems": 3488,
    "TETRIXTechTree": 8843,
    "TRAILSPlus": 2062,
    "TRPHire": 29300,
    "TUFX": 42582,
    "TWR1": 6778,
    "TacAtomicClockIrradiated": 7552,
    "TacFuelBalancer": 153167,
    "TacSelfDestructContinued": 30622,
    "TankLockRedux": 17011,
    "TantaresAndBDBNowinColors": 5523,
    "TantaresSAF": 2926,
    "TantaresSP": 8413,
    "TantaresnowinColors": 12383,
    "Targetron": 12890,
    "TarsierSpaceTechnologyWithGalaxies": 168973,
    "TeaKettleRCS": 628,
    "TechTreeKompacted": 1789,
    "TelemachusForAll": 655,
    "TelemachusReborn": 5990,
    "Telemagic": 4816,
    "TestFlight": 218657,
    "TestFlightConfig-KerbalAtomics": 3846,
    "TestFlightConfig-NFPropulsion": 3846,
    "TestFlightConfig-NFSpacecraft": 3846,
    "TestFlightConfig-Stock-S42": 3846,
    "TestFlightConfigLibrary": 3846,
    "TestFlightConfigStock": 218657,
    "TestLite": 0,
    "TextureReplacer": 430995,
    "TextureReplacerReplaced": 97959,
    "TexturesUnlimited": 255296,
    "ThalassaSystem": 2640,
    "TheBlueDrill": 2266,
    "TheBlueScoop": 1904,
    "TheGoldStandard": 7742,
    "TheMartianforKSP": 8098,
    "TheOutpost": 511,
    "ThePlodSystemII": 1328,
    "TheRATPack": 7711,
    "TheSendemiaSystem": 1016,
    "TheSereneSystem": 1373,
    "ThorTech": 24514,
    "ThrottleControlledAvionics": 211506,
    "ThrottleLimitExtended": 8199,
    "ThroughTheEyesOfaKerbal": 16977,
    "TiltEm": 363,
    "TiltUnlocker": 1014,
    "TimeControl": 45366,
    "Timekeeper": 7775,
    "Titania": 2270,
    "Titaythe35": 1815,
    "ToadicusToolsContinued": 79388,
    "ToggleLadderExit": 490,
    "TokamakRefurbishedParts": 35344,
    "TooManyOrbits": 28759,
    "Toolbar": 194281,
    "ToolbarController": 443093,
    "TopiaiSystem": 1701,
    "TotalTime": 18957,
    "TrackingLights": 8353,
    "TrackingStationAmbientlight": 3110,
    "TrackingStationEvolved": 56672,
    "Trajectories": 489842,
    "TransferWindowPlanner": 335768,
    "TransparentPods": 4768,
    "TreeToppler": 9924,
    "TrekDrive": 4017,
    "TriangulumGalaxySkybox": 1277,
    "TriggerAu-Flags": 422027,
    "TrimIndicator": 9444,
    "TrimIndicators": 4461,
    "TundraExploration": 196768,
    "TundraSpaceCenter": 63071,
    "TundraTechnologies": 196768,
    "TweakScale": 649990,
    "TweakScaleCompanion-ReStockPlus": 16399,
    "TweakableEverythingCont": 101991,
    "UICore": 14504,
    "UKS": 376114,
    "ULAVulcan": 5516,
    "UNDOCKINATOR": 17422,
    "USI-ART": 270388,
    "USI-Core": 522196,
    "USI-EXP": 467277,
    "USI-FTT": 462857,
    "USI-LS": 471400,
    "USI-NuclearRockets": 128976,
    "USITools": 569200,
    "USSDiscovery": 3002,
    "UTechNuclearScienceInk": 10716,
    "UbioWeldContinued": 75702,
    "UnKerballedStart": 20135,
    "UniversalStorage2": 100426,
    "UniversalStorageStockResourceFuelCell": 9088,
    "UrgentContracts": 1757,
    "UtilityWeight": 4790,
    "VABReorienter": 8475,
    "VOID": 12582,
    "ValorPlanetPack": 985,
    "VaporVent": 66165,
    "VariantPersist": 4517,
    "VarutaSystem": 2848,
    "VaughnsAstronikiSunflareforRSS": 2014,
    "VaughnsAstronikiSunflareforStockKSP": 1898,
    "VectorRepurposed": 5344,
    "VenStockRevamp": 460520,
    "VenStockRevamp-Core": 460520,
    "VenStockRevamp-NewParts": 460520,
    "VentralDrill": 11385,
    "VertikalSpeedIndicator": 920,
    "VesselMoverContinued": 160191,
    "VesselNotes": 498,
    "VesselView": 113370,
    "VesselView-UI-RasterPropMonitor": 113370,
    "VesselView-UI-Toolbar": 113370,
    "VexarpIVA": 4505,
    "VultureSystem": 4025,
    "WalkAbout": 17259,
    "WallacorpFlag": 1346,
    "Wanhu-Common": 3992,
    "WarpDrive": 5120,
    "WasdEditorCameraContinued": 67242,
    "WaterLaunchSites": 9707,
    "Waterfall": 120133,
    "WaterfallRestock": 34687,
    "WaypointManager": 705401,
    "WernherCheckerContinued": 17080,
    "WernhersOldBits": 25518,
    "WhereCanIGo": 7238,
    "WhirligigWorld": 5432,
    "WhoAmI": 24600,
    "WildBlue-PlayMode-CRP": 52958,
    "WildBlue-PlayMode-ClassicStock": 52958,
    "WildBlue-PlayMode-Pristine": 52958,
    "WildBlue-PlayMode-Simplified": 52958,
    "WildBlue-PlayMode-USI": 2271,
    "WildBlueTools": 52958,
    "WindTunnel": 18643,
    "WindowShineTR": 35679,
    "WorkingUnderwaterLite": 1993,
    "WorldStabilizer": 40236,
    "WorldWarMaritimeShips": 6120,
    "Wwwwwwwww": 9203,
    "Wyvern-5": 3927,
    "XDHorribleWeapons": 3579,
    "XamionAplanetfarBeyondEeloo": 3057,
    "XensPlanetCollectionRevived": 4119,
    "Xingyun2": 2234,
    "YongeTechTreesPlugin-Revived": 13202,
    "ZZZRadioTelescope": 27034,
    "ZeosPlanetPack": 1871,
    "ZeroMiniAVC": 208417,
    "kOS": 181639,
    "kOS-EVA": 2235,
    "kOS-SCANSat": 4118,
    "kOS-SpaceCore": 5342,
    "kOS-StockCamera": 4339,
    "kRPC": 38812,
    "kRPC-MechJeb": 1540,
    "notes": 13113,
    "unBlur": 31107,
    "xScienceContinued": 173817
}